lsapy/__init__.py
lsapy/aggregate.py
lsapy/criteria.py
lsapy/lsa.py
lsapy/standardize.py
lsapy/stats.py
lsapy/core/__init__.py
lsapy/core/formatting.py
lsapy/core/functions.py
lsapy/core/options.py
lsapy/data/registry.txt
lsapy/functions/__init__.py
lsapy/functions/_discrete.py
lsapy/functions/_suitability.py
lsapy/functions/membership.py
lsapy/utils/__init__.py
lsapy/utils/_utils.py
lsapy-0.3.1.dist-info/licenses/LICENSE
lsapy-0.3.1.dist-info/WHEEL
lsapy-0.3.1.dist-info/METADATA
lsapy-0.3.1.dist-info/RECORD
