Metadata-Version: 2.4
Name: lsapy
Version: 0.3.1
Summary: A Python package for Land Suitability Analysis.
Keywords: LSAPy,Land Suitability Analysis,Geospatial Analysis,GIS,Geography
Author-email: Baptiste Hamon <baptiste.hamon@pg.canterbury.ac.nz>
Maintainer-email: Baptiste Hamon <baptiste.hamon@pg.canterbury.ac.nz>
Requires-Python: >=3.10
Classifier: Development Status :: 3 - Alpha
Classifier: Intended Audience :: Developers
Classifier: Intended Audience :: Science/Research
Classifier: Natural Language :: English
Classifier: Operating System :: OS Independent
Classifier: Programming Language :: Python :: 3
Classifier: Programming Language :: Python :: 3.10
Classifier: Programming Language :: Python :: 3.11
Classifier: Programming Language :: Python :: 3.12
Classifier: Programming Language :: Python :: 3.13
Classifier: Topic :: Scientific/Engineering :: GIS
License-File: LICENSE
Requires-Dist: geopandas >=0.14.0
Requires-Dist: numpy >=1.26.0
Requires-Dist: pandas >=2.2.0
Requires-Dist: pooch >=1.8.2
Requires-Dist: regionmask >=0.13.0
Requires-Dist: scipy >=1.15.0
Requires-Dist: xarray >=2024.10.0
Requires-Dist: lsapy[dev] ; extra == "all"
Requires-Dist: lsapy[docs] ; extra == "all"
Requires-Dist: blackdoc >=0.3.9 ; extra == "dev"
Requires-Dist: bump-my-version >=1.1.4 ; extra == "dev"
Requires-Dist: codespell >=2.4.1 ; extra == "dev"
Requires-Dist: coverage[toml] >=7.7.0 ; extra == "dev"
Requires-Dist: flit >=3.11 ; extra == "dev"
Requires-Dist: h5netcdf >=1.4.0 ; extra == "dev"
Requires-Dist: ipython >=8.20.0 ; extra == "dev"
Requires-Dist: matplotlib >=3.9.0 ; extra == "dev"
Requires-Dist: mypy >=1.17.1 ; extra == "dev"
Requires-Dist: nbval >=0.11.0 ; extra == "dev"
Requires-Dist: nox >=2024.10.09 ; extra == "dev"
Requires-Dist: numpydoc >=1.8.0 ; extra == "dev"
Requires-Dist: pre-commit >=4.0.0 ; extra == "dev"
Requires-Dist: pytest >=8.3.0 ; extra == "dev"
Requires-Dist: pytest-cov >=6.0.0 ; extra == "dev"
Requires-Dist: ruff >=0.10.0 ; extra == "dev"
Requires-Dist: vulture >=2.14 ; extra == "dev"
Requires-Dist: xclim >=0.54.0 ; extra == "dev"
Requires-Dist: yamllint >=1.37.1 ; extra == "dev"
Requires-Dist: ipykernel ; extra == "docs"
Requires-Dist: matplotlib >=3.9.0 ; extra == "docs"
Requires-Dist: nbsphinx >=0.9.5 ; extra == "docs"
Requires-Dist: pybtex >=0.24.0 ; extra == "docs"
Requires-Dist: pydata-sphinx-theme >=0.16.0 ; extra == "docs"
Requires-Dist: sphinx >=8.2.0 ; extra == "docs"
Requires-Dist: sphinx-autodoc-typehints >=3.2.0 ; extra == "docs"
Requires-Dist: sphinx-copybutton ; extra == "docs"
Requires-Dist: sphinx-mdinclude ; extra == "docs"
Requires-Dist: sphinxcontrib-bibtex >=2.6.0 ; extra == "docs"
Project-URL: Homepage, https://lsapy.readthedocs.io/en/stable/
Project-URL: Issues, https://github.com/baptistehamon/lsapy/issues
Project-URL: Source, https://github.com/baptistehamon/lsapy
Project-URL: Zenodo, https://doi.org/10.5281/zenodo.15015110
Provides-Extra: all
Provides-Extra: dev
Provides-Extra: docs
